{"id":"4it4kktpaqbu2raq4bk5oub","title":"Nmap","desc":"","updated":1680236139348,"created":1678077599781,"custom":{},"fname":"Cheat Sheets.PEN_cheatsheet.Nmap","type":"note","vault":{"fsPath":".","selfContained":true,"name":"Cybersecurity_Notes"},"contentHash":"daa5849f8316e294344571c555675c3c","links":[{"from":{"fname":"Cheat Sheets","id":"t7zelcb6b17opo2gjy4y9cq","vaultName":"Cybersecurity_Notes"},"type":"backlink","position":{"start":{"line":2,"column":3,"offset":49},"end":{"line":2,"column":39,"offset":85},"indent":[]},"value":"Cheat Sheets.PEN_cheatsheet.Nmap"},{"from":{"fname":"Cheat Sheets.PEN_cheatsheet","id":"3o48nuz7byeshb4lhbfpang","vaultName":"Cybersecurity_Notes"},"type":"backlink","position":{"start":{"line":38,"column":30,"offset":1233},"end":{"line":38,"column":66,"offset":1269},"indent":[]},"value":"Cheat Sheets.PEN_cheatsheet.Nmap"},{"from":{"fname":"Cheat Sheets.PEN_cheatsheet","id":"3o48nuz7byeshb4lhbfpang","vaultName":"Cybersecurity_Notes"},"type":"backlink","position":{"start":{"line":39,"column":45,"offset":1325},"end":{"line":39,"column":81,"offset":1361},"indent":[]},"value":"Cheat Sheets.PEN_cheatsheet.Nmap"}],"anchors":{"scanning-options":{"type":"header","text":"Scanning Options","value":"scanning-options","line":7,"column":0,"depth":2},"output-options":{"type":"header","text":"Output Options","value":"output-options","line":63,"column":0,"depth":2},"performance-options":{"type":"header","text":"Performance Options","value":"performance-options","line":75,"column":0,"depth":2}},"children":[],"parent":"3o48nuz7byeshb4lhbfpang","data":{}}
