{"id":"mybr5q8teq3cgw5295vo8le","title":"Controlled_Node_Setup","desc":"","updated":1675600464838,"created":1673951621086,"custom":{},"fname":"HOT HomeLab Of Things.ANSIBLE.Controlled_Node_Setup","type":"note","vault":{"fsPath":".","selfContained":true,"name":"Cybersecurity_Notes"},"contentHash":"a4ebc8ba6bc69aaad8e6a6ab1fe3cc2c","links":[{"from":{"fname":"HOT HomeLab Of Things.ANSIBLE","id":"om8an351xireaxm8fnh4lcl","vaultName":"Cybersecurity_Notes"},"type":"backlink","position":{"start":{"line":3,"column":1,"offset":34},"end":{"line":3,"column":78,"offset":111},"indent":[]},"value":"HOT HomeLab Of Things.ANSIBLE.Controlled_Node_Setup"}],"anchors":{"controlled-node-setup":{"type":"header","text":"Controlled Node Setup","value":"controlled-node-setup","line":8,"column":0,"depth":2}},"children":[],"parent":"om8an351xireaxm8fnh4lcl","data":{}}
